tria_hr_api/__init__.py
tria_hr_api/tria_hr_api.py
tria_hr_api-1.1.2.dist-info/LICENSE
tria_hr_api-1.1.2.dist-info/METADATA
tria_hr_api-1.1.2.dist-info/WHEEL
tria_hr_api-1.1.2.dist-info/top_level.txt
tria_hr_api-1.1.2.dist-info/RECORD
